odoo/addons/account_due_list/README.rst
odoo/addons/account_due_list/__init__.py
odoo/addons/account_due_list/__manifest__.py
odoo/addons/account_due_list/init_hook.py
odoo/addons/account_due_list/i18n/account_due_list.pot
odoo/addons/account_due_list/i18n/bg.po
odoo/addons/account_due_list/i18n/da.po
odoo/addons/account_due_list/i18n/de.po
odoo/addons/account_due_list/i18n/el_GR.po
odoo/addons/account_due_list/i18n/es.po
odoo/addons/account_due_list/i18n/es_AR.po
odoo/addons/account_due_list/i18n/es_MX.po
odoo/addons/account_due_list/i18n/fi.po
odoo/addons/account_due_list/i18n/fr.po
odoo/addons/account_due_list/i18n/fr_CH.po
odoo/addons/account_due_list/i18n/fr_FR.po
odoo/addons/account_due_list/i18n/hr.po
odoo/addons/account_due_list/i18n/it.po
odoo/addons/account_due_list/i18n/nb.po
odoo/addons/account_due_list/i18n/nl.po
odoo/addons/account_due_list/i18n/pt.po
odoo/addons/account_due_list/i18n/pt_BR.po
odoo/addons/account_due_list/i18n/pt_PT.po
odoo/addons/account_due_list/i18n/sk.po
odoo/addons/account_due_list/i18n/sl.po
odoo/addons/account_due_list/i18n/tr.po
odoo/addons/account_due_list/i18n/zh_CN.po
odoo/addons/account_due_list/models/__init__.py
odoo/addons/account_due_list/models/account_move_line.py
odoo/addons/account_due_list/readme/CONFIGURE.rst
odoo/addons/account_due_list/readme/CONTRIBUTORS.rst
odoo/addons/account_due_list/readme/DESCRIPTION.rst
odoo/addons/account_due_list/readme/USAGE.rst
odoo/addons/account_due_list/static/description/icon.png
odoo/addons/account_due_list/static/description/index.html
odoo/addons/account_due_list/views/payment_view.xml
odoo14_addon_account_due_list-14.0.1.2.0.dist-info/METADATA
odoo14_addon_account_due_list-14.0.1.2.0.dist-info/WHEEL
odoo14_addon_account_due_list-14.0.1.2.0.dist-info/top_level.txt
odoo14_addon_account_due_list-14.0.1.2.0.dist-info/RECORD
